discognition/__init__.py
discognition/discognition.py
discognition/parser.py
discognition/version.py
discognition-0.2.2.data/scripts/discognition
discognition-0.2.2.dist-info/LICENSE.md
discognition-0.2.2.dist-info/METADATA
discognition-0.2.2.dist-info/WHEEL
discognition-0.2.2.dist-info/top_level.txt
discognition-0.2.2.dist-info/RECORD
