Metadata-Version: 2.1
Name: discognition
Version: 0.2.2
Summary: update mp3 metadata and file/directory names using the discogs api
Home-page: https://github.com/hdbhdb/discognition
Author: Hudson Bailey
Author-email: hudsondiggsbailey@gmail.com
License: MIT
Platform: UNKNOWN
Classifier: Programming Language :: Python :: 3
Classifier: Operating System :: OS Independent
Requires-Dist: mutagen (>=1.41.1)
Requires-Dist: discogs-client (>=2.2.2)
